x21218315
