Metadata-Version: 1.1
Name: x21218315
Version: 0.0.2
Summary: publish email 
Home-page: UNKNOWN
Author: Manoj K
Author-email: x21218315@student.ncirl.ie
License: UNKNOWN
Keywords: x21218315
Platform: UNKNOWN
Classifier: Development Status :: 5 - Production/Stable
Classifier: Intended Audience :: Education
Classifier: Operating System :: Microsoft :: Windows :: Windows 10
Classifier: License :: OSI Approved :: MIT License
Classifier: Programming Language :: Python :: 3
